xlsx_data_stream/__init__.py
xlsx_data_stream/astream.py
xlsx_data_stream/common.py
xlsx_data_stream/stream.py
xlsx_data_stream-0.0.1.dist-info/LICENCE
xlsx_data_stream-0.0.1.dist-info/METADATA
xlsx_data_stream-0.0.1.dist-info/WHEEL
xlsx_data_stream-0.0.1.dist-info/RECORD
