Metadata-Version: 2.3
Name: xlsx-data-stream
Version: 0.0.1
Summary: build xlsx files using streams
Author: Michael Kryukov
Author-email: mkrukov@bestplace.pro
Requires-Python: >=3.9
Classifier: Programming Language :: Python :: 3
Classifier: Programming Language :: Python :: 3.9
Classifier: Programming Language :: Python :: 3.10
Classifier: Programming Language :: Python :: 3.11
Classifier: Programming Language :: Python :: 3.12
Classifier: Programming Language :: Python :: 3.13
Requires-Dist: asynczipstream (>=1.0.1,<2.0.0)
Requires-Dist: openpyxl (>=3.1.5,<4.0.0)
Requires-Dist: zipstream-new (>=1.1.8,<2.0.0)
